MANIFEST.in
README.markdown
setup.py
doccito/__init__.py
doccito/__main__.py
doccito/base.html
doccito/doc_generator.py
doccito.egg-info/PKG-INFO
doccito.egg-info/SOURCES.txt
doccito.egg-info/dependency_links.txt
doccito.egg-info/entry_points.txt
doccito.egg-info/requires.txt
doccito.egg-info/top_level.txt