Metadata-Version: 1.0
Name: doccito
Version: 0.1.2
Summary: Send alerts, notifications, and messages based on events in your django application
Home-page: http://doccito.com
Author: Rootbuzz
Author-email: info@rootbuzz.com
License: MIT
Keywords: documentation
Platform: UNKNOWN
Classifier: Development Status :: 5 - Production/Stable
Classifier: License :: OSI Approved :: MIT License
Classifier: Programming Language :: Python
Classifier: Environment :: Web Environment
Classifier: Intended Audience :: Developers
Classifier: Operating System :: OS Independent
Classifier: Topic :: Internet :: WWW/HTTP
Classifier: Topic :: Utilities
